matplotlib-stubs/__init__.pyi
matplotlib-stubs/artist.pyi
matplotlib-stubs/axes.pyi
matplotlib-stubs/backend_bases.pyi
matplotlib-stubs/cm.pyi
matplotlib-stubs/collections.pyi
matplotlib-stubs/color.pyi
matplotlib-stubs/font_manager.pyi
matplotlib-stubs/image.pyi
matplotlib-stubs/legend.pyi
matplotlib-stubs/patheffects.pyi
matplotlib-stubs/pyplot.pyi
matplotlib-stubs/style.pyi
matplotlib-stubs/text.pyi
matplotlib-stubs/transforms.pyi
numpy-stubs/__init__.pyi
numpy-stubs/linalg.pyi
numpy-stubs/ma.pyi
numpy-stubs/random.pyi
numpy-stubs/testing.pyi
pandas-stubs/__init__.pyi
pandas-stubs/testing.pyi
pandas-stubs/core/__init__.pyi
pandas-stubs/core/frame.pyi
pandas-stubs/core/indexing.pyi
pandas-stubs/core/series.pyi
pandas-stubs/core/strings.pyi
pandas-stubs/core/arrays/__init__.pyi
pandas-stubs/core/arrays/base.pyi
pandas-stubs/core/arrays/integer.pyi
pandas-stubs/core/arrays/masked.pyi
pandas-stubs/core/dtypes/__init__.pyi
pandas-stubs/core/dtypes/base.pyi
pandas-stubs/core/groupby/__init__.pyi
pandas-stubs/core/groupby/generic.pyi
pandas-stubs/core/indexes/__init__.pyi
pandas-stubs/core/indexes/base.pyi
pandas-stubs/core/indexes/frozen.pyi
pandas-stubs/core/indexes/multi.pyi
data_science_types-0.2.23.dist-info/LICENSE
data_science_types-0.2.23.dist-info/METADATA
data_science_types-0.2.23.dist-info/WHEEL
data_science_types-0.2.23.dist-info/top_level.txt
data_science_types-0.2.23.dist-info/RECORD
