Metadata-Version: 2.1
Name: data-science-types
Version: 0.2.23
Summary: Type stubs for Python machine learning libraries
Home-page: https://github.com/predictive-analytics-lab/data-science-types
Author: PAL
License: Apache License 2.0
Project-URL: Bug Tracker, https://github.com/predictive-analytics-lab/data-science-types/issues/
Project-URL: Source Code, https://github.com/predictive-analytics-lab/data-science-types
Platform: UNKNOWN
Classifier: Programming Language :: Python :: 3
Classifier: License :: OSI Approved :: Apache Software License
Classifier: Typing :: Typed
Requires-Python: >=3.6
Provides-Extra: dev
